skytemple_files/__init__.py
skytemple_files/export_maps.py
skytemple_files/py.typed
skytemple_files/user_error.py
skytemple_files/_resources/patches/LICENSE
skytemple_files/_resources/patches/README.rst
skytemple_files/_resources/patches/asm_patches/disarm_one_room_mh.asm
skytemple_files/_resources/patches/asm_patches/header_stub_eu.asm
skytemple_files/_resources/patches/asm_patches/header_stub_jp.asm
skytemple_files/_resources/patches/asm_patches/header_stub_na.asm
skytemple_files/_resources/patches/asm_patches/adex_asm_mods/add_key_check/selector_overlay29.asm
skytemple_files/_resources/patches/asm_patches/adex_asm_mods/add_key_check/selector_overlay36.asm
skytemple_files/_resources/patches/asm_patches/adex_asm_mods/add_key_check/common/key_ov29.asm
skytemple_files/_resources/patches/asm_patches/adex_asm_mods/add_key_check/common/key_ov36.asm
skytemple_files/_resources/patches/asm_patches/adex_asm_mods/add_key_check/eu/offsets.asm
skytemple_files/_resources/patches/asm_patches/adex_asm_mods/add_key_check/jp/offsets.asm
skytemple_files/_resources/patches/asm_patches/adex_asm_mods/add_key_check/na/offsets.asm
skytemple_files/_resources/patches/asm_patches/adex_asm_mods/bold_text/selector_arm9.asm
skytemple_files/_resources/patches/asm_patches/adex_asm_mods/bold_text/selector_overlay36.asm
skytemple_files/_resources/patches/asm_patches/adex_asm_mods/bold_text/common/bold_arm9.asm
skytemple_files/_resources/patches/asm_patches/adex_asm_mods/bold_text/common/bold_ov36.asm
skytemple_files/_resources/patches/asm_patches/adex_asm_mods/bold_text/eu/offsets.asm
skytemple_files/_resources/patches/asm_patches/adex_asm_mods/bold_text/jp/offsets.asm
skytemple_files/_resources/patches/asm_patches/adex_asm_mods/bold_text/na/offsets.asm
skytemple_files/_resources/patches/asm_patches/adex_asm_mods/change_portrait/selector_arm9.asm
skytemple_files/_resources/patches/asm_patches/adex_asm_mods/change_portrait/selector_overlay29.asm
skytemple_files-1.8.4.dist-info/LICENSE
skytemple_files-1.8.4.dist-info/METADATA
skytemple_files-1.8.4.dist-info/WHEEL
skytemple_files-1.8.4.dist-info/entry_points.txt
skytemple_files-1.8.4.dist-info/top_level.txt
skytemple_files-1.8.4.dist-info/RECORD
