Metadata-Version: 2.1
Name: skytemple-files
Version: 1.8.4
Summary: Python library to edit the ROM of Pokémon Mystery Dungeon Explorers of Sky
Author-email: "Marco \"Capypara\" Köpcke" <hello@capypara.de>
License: GPL-3.0-or-later
Project-URL: Homepage, https://skytemple.org
Project-URL: Announcements, https://blog.skytemple.org
Project-URL: Documentation, https://wiki.skytemple.org
Project-URL: Repository, https://github.com/SkyTemple/skytemple-files.git
Project-URL: Issues, https://github.com/SkyTemple/skytemple-files/issues
Project-URL: Discord, https://discord.gg/skytemple
Keywords: rom-hacking,game-modding,skytemple
Classifier: Development Status :: 4 - Beta
Classifier: Programming Language :: Python
Classifier: License :: OSI Approved :: GNU General Public License v3 or later (GPLv3+)
Classifier: Programming Language :: Python :: 3.10
Classifier: Programming Language :: Python :: 3.11
Classifier: Programming Language :: Python :: 3.12
Classifier: Programming Language :: Python :: 3.13
Requires-Python: >=3.10
License-File: LICENSE
Requires-Dist: pmdsky-debug-py==10.0.48
Requires-Dist: ndspy>=3.0.0
Requires-Dist: range-typed-integers>=1.0.1
Requires-Dist: Pillow>=6.1.0
Requires-Dist: appdirs>=1.4.0
Requires-Dist: explorerscript<0.3.0,>=0.2.2
Requires-Dist: skytemple-rust<1.9.0,>=1.8.5
Requires-Dist: pyobjc==10.3.2; sys_platform == "darwin"
Requires-Dist: dungeon-eos==0.0.5
Provides-Extra: spritecollab
Requires-Dist: gql[aiohttp]>=3.5.0; extra == "spritecollab"
Requires-Dist: graphql-core>=3.2.0; extra == "spritecollab"
Requires-Dist: aiohttp[speedups]; extra == "spritecollab"
Requires-Dist: lru-dict>=1.1.8; extra == "spritecollab"
